{"mean":{"confidence_interval":{"confidence_level":0.95,"lower_bound":300297988.992,"upper_bound":303377485.50549996},"point_estimate":301815417.26,"standard_error":786092.9468306111},"median":{"confidence_interval":{"confidence_level":0.95,"lower_bound":299066286.5,"upper_bound":303338559.0},"point_estimate":300391251.5,"standard_error":993991.3091292831},"median_abs_dev":{"confidence_interval":{"confidence_level":0.95,"lower_bound":5355003.586229682,"upper_bound":9067593.299818039},"point_estimate":6513201.7900675535,"standard_error":950941.9405131742},"slope":null,"std_dev":{"confidence_interval":{"confidence_level":0.95,"lower_bound":6546977.992406115,"upper_bound":9282976.271233132},"point_estimate":7954260.1109624375,"standard_error":700332.3826583258}}